pydantic_market_data/__init__.py
pydantic_market_data/interfaces.py
pydantic_market_data/models.py
pydantic_market_data/py.typed
pydantic_market_data-0.1.6.dist-info/METADATA
pydantic_market_data-0.1.6.dist-info/WHEEL
pydantic_market_data-0.1.6.dist-info/licenses/LICENSE
pydantic_market_data-0.1.6.dist-info/RECORD
