Metadata-Version: 2.4
Name: pydantic-market-data
Version: 0.1.6
Summary: Shared models and interfaces for finance datasources
Project-URL: Homepage, https://github.com/romamo/pydantic-market-data
Project-URL: Repository, https://github.com/romamo/pydantic-market-data
Project-URL: Issues, https://github.com/romamo/pydantic-market-data/issues
Author-email: Roman Medvedev <pypi@romavm.dev>
License: MIT
License-File: LICENSE
Classifier: Development Status :: 4 - Beta
Classifier: Intended Audience :: Developers
Classifier: License :: OSI Approved :: MIT License
Classifier: Programming Language :: Python
Classifier: Programming Language :: Python :: 3.10
Classifier: Programming Language :: Python :: 3.11
Classifier: Programming Language :: Python :: 3.12
Classifier: Programming Language :: Python :: 3.13
Classifier: Programming Language :: Python :: 3.14
Classifier: Programming Language :: Python :: Implementation :: CPython
Classifier: Programming Language :: Python :: Implementation :: PyPy
Requires-Python: >=3.11
Requires-Dist: pandas>=3.0.0
Requires-Dist: pycountry>=24.6.1
Requires-Dist: pydantic-extra-types>=2.11.0
Requires-Dist: pydantic>=2.0.0
